vonage_cloud_runtime/IBridge.py
vonage_cloud_runtime/IVCR.py
vonage_cloud_runtime/__init__.py
vonage_cloud_runtime/bridge.py
vonage_cloud_runtime/errors/ISdkError.py
vonage_cloud_runtime/errors/__init__.py
vonage_cloud_runtime/providers/__init__.py
vonage_cloud_runtime/providers/assets/IAssets.py
vonage_cloud_runtime/providers/assets/__init__.py
vonage_cloud_runtime/providers/assets/assets.py
vonage_cloud_runtime/providers/assets/contracts/__init__.py
vonage_cloud_runtime/providers/assets/contracts/assetInfo.py
vonage_cloud_runtime/providers/assets/contracts/assetLinkResponse.py
vonage_cloud_runtime/providers/assets/contracts/assetListResponse.py
vonage_cloud_runtime/providers/assets/contracts/directoryPayload.py
vonage_cloud_runtime/providers/assets/contracts/getAssetPayload.py
vonage_cloud_runtime/providers/assets/contracts/getAssetResponse.py
vonage_cloud_runtime/providers/assets/contracts/linkPayload.py
vonage_cloud_runtime/providers/assets/contracts/listAssetsPayload.py
vonage_cloud_runtime/providers/assets/contracts/removeAssetPayload.py
vonage_cloud_runtime/providers/assets/enums/__init__.py
vonage_cloud_runtime/providers/assets/enums/assetsAction.py
vonage_cloud_runtime/providers/assets/enums/fileRetentionPeriod.py
vonage_cloud_runtime/providers/conversation/IConversation.py
vonage_cloud_runtime/providers/conversation/__init__.py
vonage_cloud_runtime/providers/conversation/contracts/IConversationEventCallback.py
vonage_cloud_runtime/providers/conversation/contracts/__init__.py
vonage_cloud_runtime/providers/conversation/contracts/conversationPayloadWithCallback.py
vonage_cloud_runtime/providers/conversation/conversation.py
vonage_cloud_runtime/providers/conversation/enums/__init__.py
vonage_cloud_runtime/providers/conversation/enums/conversationAction.py
vonage_cloud_runtime/providers/events/IEventEmitter.py
vonage_cloud_runtime/providers/events/IEventFactory.py
vonage_cloud_runtime/providers/events/__init__.py
vonage_cloud_runtime-2.0.0.dist-info/LICENSE.txt
vonage_cloud_runtime-2.0.0.dist-info/METADATA
vonage_cloud_runtime-2.0.0.dist-info/WHEEL
vonage_cloud_runtime-2.0.0.dist-info/RECORD
