Metadata-Version: 2.3
Name: vonage_cloud_runtime
Version: 2.0.0
Summary: Python SDK for Vonage Cloud Runtime
License: Apache
Author: Vonage
Author-email: devrel@vonage.com
Requires-Python: >=3.10.5,<4.0.0
Classifier: License :: Other/Proprietary License
Classifier: Programming Language :: Python :: 3
Classifier: Programming Language :: Python :: 3.11
Classifier: Programming Language :: Python :: 3.12
Classifier: Programming Language :: Python :: 3.13
Requires-Dist: PyJWT[crypto]
Requires-Dist: aiohttp
Requires-Dist: pendulum
Requires-Dist: requests
